verify_email/__init__.py
verify_email/admin.py
verify_email/app_configurations.py
verify_email/apps.py
verify_email/confirm.py
verify_email/custom_types.py
verify_email/email_handler.py
verify_email/errors.py
verify_email/forms.py
verify_email/interface.py
verify_email/models.py
verify_email/signals.py
verify_email/tests.py
verify_email/token_manager.py
verify_email/urls.py
verify_email/views.py
verify_email/migrations/0001_initial.py
verify_email/migrations/__init__.py
verify_email/templates/email_index.html
verify_email/templates/verify_email/email_verification_failed.html
verify_email/templates/verify_email/email_verification_msg.html
verify_email/templates/verify_email/email_verification_successful.html
verify_email/templates/verify_email/link_expired.html
verify_email/templates/verify_email/new_email_sent.html
verify_email/templates/verify_email/request_new_email.html
Django_Verify_Email-3.0.2.dist-info/LICENSE
Django_Verify_Email-3.0.2.dist-info/METADATA
Django_Verify_Email-3.0.2.dist-info/WHEEL
Django_Verify_Email-3.0.2.dist-info/top_level.txt
Django_Verify_Email-3.0.2.dist-info/RECORD
