Metadata-Version: 2.1
Name: Django-Verify-Email
Version: 3.0.2
Summary: A Django app for email verification.
Home-page: https://github.com/foo290/Django-Verify-Email/
Author: Nitin
Author-email: ns290670@gamil.com
Classifier: Environment :: Web Environment
Classifier: Framework :: Django CMS :: 3.8
Classifier: Intended Audience :: Developers
Classifier: Programming Language :: Python :: 3.6
Classifier: License :: OSI Approved :: MIT License
Classifier: Operating System :: OS Independent
License-File: LICENSE
